Metadata-Version: 1.0
Name: sagemakerdevcloudrp
Version: 0.1.2
Summary: The Sagemaker client to run outside the AWS environment.
Home-page: UNKNOWN
Author: UNKNOWN
Author-email: UNKNOWN
License: UNKNOWN
Keywords: sagemaker
Platform: UNKNOWN
